{
  "name": "Hunt",
  "location": "forest",
  "hp": 97,
  "maxHp": 100,
  "inventory": [
    "Health Potion"
  ],
  "stats": {
    "strength": 40,
    "defense": 20,
    "dexterity": 2,
    "presence": 8
  },
  "reputation": {
    "title": "Trusted Voice",
    "score": 89,
    "breakdown": [
      {
        "title": "Trusted Voice",
        "score": 89
      },
      {
        "title": "Protector of the Realm",
        "score": 65
      },
      {
        "title": "Public Menace",
        "score": 55
      },
      {
        "title": "Unknown Figure",
        "score": 5
      },
      {
        "title": "Known Opportunist",
        "score": -33
      },
      {
        "title": "Unreliable Coward",
        "score": -106
      }
    ]
  },
  "flags": {
    "knownTroublemaker": false,
    "helpedTownsfolk": false,
    "bartenderBarred": false,
    "blockedFromStreet": false,
    "wantedByGuards": false,
    "completedIntroQuest": true
  },
  "resources": {
    "gold": 6,
    "wood": 50,
    "stone": 10
  },
  "progression": {
    "actionCounts": {
      "search": 27,
      "wait": 23,
      "defend": 142,
      "run": 2,
      "attack": 195
    },
    "actionPoints": {
      "search": 27,
      "wait": 23,
      "defend": 142,
      "run": 2,
      "attack": 195
    }
  },
  "title": "Slayer",
  "skills": [
    "Heavy Strike",
    "Blood Rush"
  ],
  "traits": {
    "honor": 71,
    "greed": 27,
    "fear": 1,
    "influence": 47,
    "chaos": 65
  },
  "introLog": [],
  "instance": null,
  "introQuest": {
    "completed": true,
    "active": false
  },
  "titleDebug": [
    {
      "title": "Slayer",
      "score": 415
    },
    {
      "title": "Guardian",
      "score": 361
    }
  ]
}